[{"tempoInatividadeCPU": 156795.13, "porcentagemCPU": 15.9, "bytesRAM": 6165385216, "porcentagemRAM": 83.6, "bytesDisco": 137785348096, "porcentagemDisco": 61.2, "processos": ["python"], "dataHora": "2024-11-13T14:23:32.714221"}, {"tempoInatividadeCPU": 156802.48, "porcentagemCPU": 9.4, "bytesRAM": 6174248960, "porcentagemRAM": 83.7, "bytesDisco": 137785425920, "porcentagemDisco": 61.2, "processos": ["python"], "dataHora": "2024-11-13T14:23:34.816351"}, {"tempoInatividadeCPU": 156813.65, "porcentagemCPU": 4.8, "bytesRAM": 6164357120, "porcentagemRAM": 83.6, "bytesDisco": 137788645376, "porcentagemDisco": 61.2, "processos": ["python"], "dataHora": "2024-11-13T14:23:37.858881"}, {"tempoInatividadeCPU": 156825.02, "porcentagemCPU": 6.8, "bytesRAM": 6169591808, "porcentagemRAM": 83.6, "bytesDisco": 137788755968, "porcentagemDisco": 61.2, "processos": ["python"], "dataHora": "2024-11-13T14:23:40.920462"}, {"tempoInatividadeCPU": 156836.41, "porcentagemCPU": 4.5, "bytesRAM": 6169837568, "porcentagemRAM": 83.6, "bytesDisco": 137788755968, "porcentagemDisco": 61.2, "processos": ["python"], "dataHora": "2024-11-13T14:23:43.961428"}, {"tempoInatividadeCPU": 156847.74, "porcentagemCPU": 4.1, "bytesRAM": 6178635776, "porcentagemRAM": 83.7, "bytesDisco": 137788760064, "porcentagemDisco": 61.2, "processos": ["python"], "dataHora": "2024-11-13T14:23:47.003752"}, {"tempoInatividadeCPU": 156859.17, "porcentagemCPU": 4.8, "bytesRAM": 6175784960, "porcentagemRAM": 83.7, "bytesDisco": 137788760064, "porcentagemDisco": 61.2, "processos": ["python"], "dataHora": "2024-11-13T14:23:50.046419"}, {"tempoInatividadeCPU": 156870.51, "porcentagemCPU": 4.3, "bytesRAM": 6172524544, "porcentagemRAM": 83.7, "bytesDisco": 137788760064, "porcentagemDisco": 61.2, "processos": ["python"], "dataHora": "2024-11-13T14:23:53.088447"}, {"tempoInatividadeCPU": 156881.93, "porcentagemCPU": 5.1, "bytesRAM": 6174609408, "porcentagemRAM": 83.7, "bytesDisco": 137788764160, "porcentagemDisco": 61.2, "processos": ["jetbrains-toolbox", "python"], "dataHora": "2024-11-13T14:23:56.151230"}, {"tempoInatividadeCPU": 156893.38, "porcentagemCPU": 5.8, "bytesRAM": 6174248960, "porcentagemRAM": 83.7, "bytesDisco": 137788764160, "porcentagemDisco": 61.2, "processos": ["python"], "dataHora": "2024-11-13T14:23:59.215848"}, {"tempoInatividadeCPU": 156904.73, "porcentagemCPU": 4.1, "bytesRAM": 6176436224, "porcentagemRAM": 83.7, "bytesDisco": 137788764160, "porcentagemDisco": 61.2, "processos": ["python"], "dataHora": "2024-11-13T14:24:02.259671"}, {"tempoInatividadeCPU": 156916.0, "porcentagemCPU": 8.1, "bytesRAM": 6189314048, "porcentagemRAM": 83.8, "bytesDisco": 137776185344, "porcentagemDisco": 61.2, "processos": ["python"], "dataHora": "2024-11-13T14:24:05.303970"}, {"tempoInatividadeCPU": 156927.27, "porcentagemCPU": 4.1, "bytesRAM": 6191169536, "porcentagemRAM": 83.8, "bytesDisco": 137776185344, "porcentagemDisco": 61.2, "processos": ["python"], "dataHora": "2024-11-13T14:24:08.366057"}, {"tempoInatividadeCPU": 156938.06, "porcentagemCPU": 39.9, "bytesRAM": 6174257152, "porcentagemRAM": 84.0, "bytesDisco": 137776185344, "porcentagemDisco": 61.2, "processos": ["python"], "dataHora": "2024-11-13T14:24:11.438110"}, {"tempoInatividadeCPU": 156947.24, "porcentagemCPU": 21.4, "bytesRAM": 6186106880, "porcentagemRAM": 84.1, "bytesDisco": 137776189440, "porcentagemDisco": 61.2, "processos": ["gnome-shell", "python"], "dataHora": "2024-11-13T14:24:14.487198"}, {"tempoInatividadeCPU": 156956.23, "porcentagemCPU": 50.5, "bytesRAM": 6185574400, "porcentagemRAM": 84.2, "bytesDisco": 137776189440, "porcentagemDisco": 61.2, "processos": ["Xorg", "code", "python"], "dataHora": "2024-11-13T14:24:17.584947"}, {"tempoInatividadeCPU": 156962.32, "porcentagemCPU": 13.7, "bytesRAM": 6182182912, "porcentagemRAM": 83.9, "bytesDisco": 137776189440, "porcentagemDisco": 61.2, "processos": ["python"], "dataHora": "2024-11-13T14:24:20.651856"}, {"tempoInatividadeCPU": 156971.38, "porcentagemCPU": 24.2, "bytesRAM": 6179536896, "porcentagemRAM": 83.8, "bytesDisco": 137776201728, "porcentagemDisco": 61.2, "processos": ["python"], "dataHora": "2024-11-13T14:24:23.735402"}, {"tempoInatividadeCPU": 156978.74, "porcentagemCPU": 50.9, "bytesRAM": 6179110912, "porcentagemRAM": 83.8, "bytesDisco": 137776209920, "porcentagemDisco": 61.2, "processos": ["gnome-shell", "python"], "dataHora": "2024-11-13T14:24:26.849000"}, {"tempoInatividadeCPU": 156986.1, "porcentagemCPU": 36.1, "bytesRAM": 6176550912, "porcentagemRAM": 83.7, "bytesDisco": 137776205824, "porcentagemDisco": 61.2, "processos": ["python"], "dataHora": "2024-11-13T14:24:29.909235"}, {"tempoInatividadeCPU": 156993.1, "porcentagemCPU": 21.2, "bytesRAM": 6189596672, "porcentagemRAM": 83.9, "bytesDisco": 137776238592, "porcentagemDisco": 61.2, "processos": ["Xorg", "gnome-shell", "python"], "dataHora": "2024-11-13T14:24:33.024735"}, {"tempoInatividadeCPU": 157002.46, "porcentagemCPU": 14.4, "bytesRAM": 6175637504, "porcentagemRAM": 83.7, "bytesDisco": 137776238592, "porcentagemDisco": 61.2, "processos": ["Xorg", "python"], "dataHora": "2024-11-13T14:24:36.123844"}, {"tempoInatividadeCPU": 157009.26, "porcentagemCPU": 42.1, "bytesRAM": 6171492352, "porcentagemRAM": 83.7, "bytesDisco": 137776250880, "porcentagemDisco": 61.2, "processos": ["python"], "dataHora": "2024-11-13T14:24:39.185954"}, {"tempoInatividadeCPU": 157017.59, "porcentagemCPU": 59.6, "bytesRAM": 6193893376, "porcentagemRAM": 83.9, "bytesDisco": 137776259072, "porcentagemDisco": 61.2, "processos": ["python"], "dataHora": "2024-11-13T14:24:42.239850"}, {"tempoInatividadeCPU": 157024.88, "porcentagemCPU": 14.0, "bytesRAM": 6190813184, "porcentagemRAM": 83.8, "bytesDisco": 137776259072, "porcentagemDisco": 61.2, "processos": ["python"], "dataHora": "2024-11-13T14:24:45.308310"}, {"tempoInatividadeCPU": 157034.37, "porcentagemCPU": 16.7, "bytesRAM": 6191710208, "porcentagemRAM": 84.0, "bytesDisco": 137776259072, "porcentagemDisco": 61.2, "processos": ["code", "code", "python"], "dataHora": "2024-11-13T14:24:48.388075"}]